{
  "uid" : "40701f38477d4050",
  "name" : "dropDownMenuHeaderSecondPart",
  "title" : "Drop down menu header second part",
  "time" : {
    "start" : 1498204471723,
    "stop" : 1498204702451,
    "duration" : 230728
  },
  "summary" : {
    "attachments" : 0,
    "steps" : 0
  },
  "failure" : null,
  "description" : null,
  "severity" : "NORMAL",
  "status" : "PASSED",
  "testId" : null,
  "suite" : {
    "uid" : "8dee076e925821ad",
    "name" : "Suite",
    "title" : "Suite : Parallel Tests"
  },
  "steps" : [ ],
  "attachments" : [ ],
  "issues" : [ ],
  "labels" : [ {
    "name" : "language",
    "value" : "JAVA"
  }, {
    "name" : "suite-name",
    "value" : "Suite"
  }, {
    "name" : "framework",
    "value" : "TestNG"
  }, {
    "name" : "suite-title",
    "value" : "Suite : Parallel Tests"
  } ],
  "parameters" : [ ]
}