{
  "uid" : "64d34ee236d56fde",
  "name" : "seoOnMainSearchPageCar",
  "title" : "Seo on main search page car",
  "time" : {
    "start" : 1498028783012,
    "stop" : 1498028790358,
    "duration" : 7346
  },
  "summary" : {
    "attachments" : 0,
    "steps" : 0
  },
  "failure" : null,
  "description" : null,
  "severity" : "NORMAL",
  "status" : "PASSED",
  "testId" : null,
  "suite" : {
    "uid" : "4bd45bc62ae2ec73",
    "name" : "Default Suite",
    "title" : "Default Suite : AvtomationTestsAvtopoisk"
  },
  "steps" : [ ],
  "attachments" : [ ],
  "issues" : [ ],
  "labels" : [ {
    "name" : "language",
    "value" : "JAVA"
  }, {
    "name" : "suite-name",
    "value" : "Default Suite"
  }, {
    "name" : "framework",
    "value" : "TestNG"
  }, {
    "name" : "suite-title",
    "value" : "Default Suite : AvtomationTestsAvtopoisk"
  } ],
  "parameters" : [ ]
}